{"blobs": {"B5": {"id": "B5", "polygon": [[295, 286], [288, 284], [283, 277], [280, 271], [283, 261], [290, 253], [300, 252], [304, 253], [313, 255], [318, 261], [319, 268], [318, 277], [313, 284], [304, 288], [295, 286]]}, "B6": {"id": "B6", "polygon": [[192, 266], [181, 261], [175, 253], [175, 247], [179, 241], [186, 231], [194, 229], [205, 233], [212, 240], [216, 248], [213, 257], [210, 261], [200, 266], [192, 265]]}, "B1": {"id": "B1", "polygon": [[300, 86], [289, 84], [283, 79], [280, 71], [280, 62], [288, 55], [297, 50], [309, 53], [318, 59], [321, 68], [319, 79], [310, 85], [302, 85]]}, "B7": {"id": "B7", "polygon": [[137, 189], [127, 188], [121, 182], [116, 174], [116, 165], [120, 159], [128, 152], [139, 151], [147, 155], [153, 161], [155, 170], [151, 180], [146, 186], [133, 192]]}, "B3": {"id": "B3", "polygon": [[459, 188], [452, 186], [446, 179], [443, 169], [447, 161], [457, 152], [467, 152], [478, 156], [482, 164], [482, 174], [478, 183], [470, 188], [460, 189]]}, "B0": {"id": "B0", "polygon": [[198, 107], [188, 104], [181, 95], [181, 84], [186, 74], [197, 68], [205, 71], [217, 77], [221, 89], [216, 98], [206, 109], [198, 108]]}, "B4": {"id": "B4", "polygon": [[403, 260], [393, 258], [388, 251], [388, 241], [390, 233], [398, 229], [405, 225], [417, 227], [423, 231], [427, 239], [427, 246], [424, 252], [418, 260], [412, 260], [403, 261]]}, "B2": {"id": "B2", "polygon": [[390, 101], [379, 98], [374, 89], [373, 82], [378, 74], [385, 70], [393, 66], [404, 68], [412, 76], [414, 86], [408, 97], [399, 102], [391, 99]]}, "B8": {"id": "B8", "polygon": [[295, 199], [285, 199], [273, 191], [270, 179], [267, 165], [272, 152], [283, 143], [294, 140], [309, 141], [321, 150], [327, 164], [327, 177], [322, 189], [313, 195], [306, 199], [296, 199]]}}, "arrowHeads": {"H5": {"orientation": 225.0, "id": "H5", "rectangle": [[529, 56], [545, 74]]}, "H1": {"orientation": 0.0, "id": "H1", "rectangle": [[76, 128], [89, 141]]}, "H4": {"orientation": 0.0, "id": "H4", "rectangle": [[79, 246], [89, 257]]}, "H2": {"orientation": 0.0, "id": "H2", "rectangle": [[76, 165], [92, 177]]}, "H3": {"orientation": 0.0, "id": "H3", "rectangle": [[77, 206], [89, 216]]}, "H0": {"orientation": 0.0, "id": "H0", "rectangle": [[74, 92], [95, 103]]}, "H6": {"orientation": 0.0, "id": "H6", "rectangle": [[79, 56], [87, 65]]}}, "semantic_frame": {"motion": 0, "none": 0, "direction": 1}, "containers": {}, "imageConsts": {"I0": {"id": "I0"}}, "relationships": {"A12+H2": {"destination": "H2", "origin": "A12", "id": "A12+H2", "hasDirectionality": false, "category": "arrowHeadTail"}, "T14+B5": {"destination": "B5", "origin": "T14", "id": "T14+B5", "hasDirectionality": false, "category": "intraObjectLabel"}, "B4+A5+B5": {"id": "B4+A5+B5", "hasDirectionality": false, "category": "interObjectLinkage", "connector": "A5", "destination": "B5", "origin": "B4"}, "B1+A2+B2": {"id": "B1+A2+B2", "hasDirectionality": false, "category": "interObjectLinkage", "connector": "A2", "destination": "B2", "origin": "B1"}, "A13+H3": {"destination": "H3", "origin": "A13", "id": "A13+H3", "hasDirectionality": false, "category": "arrowHeadTail"}, "B2+A3+B3": {"id": "B2+A3+B3", "hasDirectionality": false, "category": "interObjectLinkage", "connector": "A3", "destination": "B3", "origin": "B2"}, "T1+A8": {"destination": "A8", "origin": "T1", "id": "T1+A8", "hasDirectionality": false, "category": "arrowDescriptor"}, "B5+A6+B6": {"id": "B5+A6+B6", "hasDirectionality": false, "category": "interObjectLinkage", "connector": "A6", "destination": "B6", "origin": "B5"}, "T11+B6": {"destination": "B6", "origin": "T11", "id": "T11+B6", "hasDirectionality": false, "category": "intraObjectLabel"}, "T12+B5": {"destination": "B5", "origin": "T12", "id": "T12+B5", "hasDirectionality": false, "category": "intraObjectLabel"}, "B0+A1+B1": {"id": "B0+A1+B1", "hasDirectionality": false, "category": "interObjectLinkage", "connector": "A1", "destination": "B1", "origin": "B0"}, "A9+H6": {"destination": "H6", "origin": "A9", "id": "A9+H6", "hasDirectionality": false, "category": "arrowHeadTail"}, "T0+B1": {"destination": "B1", "origin": "T0", "id": "T0+B1", "hasDirectionality": false, "category": "intraObjectLabel"}, "B6+A7+B7": {"id": "B6+A7+B7", "hasDirectionality": false, "category": "interObjectLinkage", "connector": "A7", "destination": "B7", "origin": "B6"}, "T10+B7": {"destination": "B7", "origin": "T10", "id": "T10+B7", "hasDirectionality": false, "category": "intraObjectLabel"}, "T8+B7": {"destination": "B7", "origin": "T8", "id": "T8+B7", "hasDirectionality": false, "category": "intraObjectLabel"}, "A14+H4": {"destination": "H4", "origin": "A14", "id": "A14+H4", "hasDirectionality": false, "category": "arrowHeadTail"}, "T3+B1": {"destination": "B1", "origin": "T3", "id": "T3+B1", "hasDirectionality": false, "category": "intraObjectLabel"}, "T7+B8": {"destination": "B8", "origin": "T7", "id": "T7+B8", "hasDirectionality": false, "category": "intraObjectLabel"}, "T2+B0": {"destination": "B0", "origin": "T2", "id": "T2+B0", "hasDirectionality": false, "category": "intraObjectLabel"}, "T9+A9": {"destination": "A9", "origin": "T9", "id": "T9+A9", "hasDirectionality": false, "category": "arrowDescriptor"}, "T5+B3": {"destination": "B3", "origin": "T5", "id": "T5+B3", "hasDirectionality": false, "category": "intraObjectLabel"}, "B0+A0+B7": {"id": "B0+A0+B7", "hasDirectionality": false, "category": "interObjectLinkage", "connector": "A0", "destination": "B7", "origin": "B0"}, "A8+H5": {"destination": "H5", "origin": "A8", "id": "A8+H5", "hasDirectionality": false, "category": "arrowHeadTail"}, "T4+B2": {"destination": "B2", "origin": "T4", "id": "T4+B2", "hasDirectionality": false, "category": "intraObjectLabel"}, "A10+H0": {"destination": "H0", "origin": "A10", "id": "A10+H0", "hasDirectionality": false, "category": "arrowHeadTail"}, "T6+B3": {"destination": "B3", "origin": "T6", "id": "T6+B3", "hasDirectionality": false, "category": "intraObjectLabel"}, "A11+H1": {"destination": "H1", "origin": "A11", "id": "A11+H1", "hasDirectionality": false, "category": "arrowHeadTail"}, "T13+B4": {"destination": "B4", "origin": "T13", "id": "T13+B4", "hasDirectionality": false, "category": "intraObjectLabel"}, "B3+A4+B4": {"id": "B3+A4+B4", "hasDirectionality": false, "category": "interObjectLinkage", "connector": "A4", "destination": "B4", "origin": "B3"}}, "arrows": {"A7": {"id": "A7", "polygon": [[176, 241], [157, 228], [144, 213], [132, 187], [140, 183], [149, 204], [162, 219], [183, 235], [176, 241]]}, "A9": {"id": "A9", "polygon": [[11, 66], [78, 67], [79, 71], [96, 64], [77, 50], [76, 56], [10, 58], [11, 66]]}, "A4": {"id": "A4", "polygon": [[460, 188], [459, 201], [437, 227], [423, 239], [421, 231], [435, 216], [453, 188], [460, 187]]}, "A12": {"id": "A12", "polygon": [[11, 177], [79, 177], [78, 183], [93, 171], [80, 163], [78, 169], [11, 167], [11, 180]]}, "A11": {"id": "A11", "polygon": [[10, 139], [82, 140], [82, 146], [97, 135], [79, 125], [79, 132], [12, 129], [10, 138]]}, "A5": {"id": "A5", "polygon": [[391, 253], [379, 262], [326, 274], [316, 273], [316, 266], [334, 262], [364, 258], [385, 248], [391, 254]]}, "A1": {"id": "A1", "polygon": [[222, 83], [254, 76], [282, 73], [282, 64], [255, 65], [217, 73], [222, 85]]}, "A8": {"id": "A8", "polygon": [[537, 76], [561, 109], [573, 145], [572, 183], [561, 212], [551, 230], [530, 257], [497, 284], [459, 303], [411, 321], [354, 328], [324, 328], [322, 342], [370, 343], [447, 324], [490, 303], [527, 278], [565, 237], [583, 195], [585, 165], [580, 122], [571, 99], [549, 68], [550, 64], [526, 56], [531, 82], [537, 78]]}, "A14": {"id": "A14", "polygon": [[11, 257], [82, 258], [80, 264], [95, 252], [84, 241], [80, 245], [12, 245], [13, 257]]}, "A2": {"id": "A2", "polygon": [[316, 72], [372, 84], [376, 74], [319, 64], [315, 76]]}, "A13": {"id": "A13", "polygon": [[10, 215], [78, 216], [78, 224], [93, 210], [79, 200], [78, 207], [10, 205], [11, 213]]}, "A3": {"id": "A3", "polygon": [[411, 90], [439, 107], [458, 133], [464, 156], [454, 157], [445, 137], [430, 117], [404, 97], [409, 90]]}, "A6": {"id": "A6", "polygon": [[279, 274], [252, 272], [209, 258], [213, 251], [255, 261], [282, 265], [280, 272]]}, "A0": {"id": "A0", "polygon": [[180, 102], [155, 128], [141, 152], [131, 150], [139, 133], [158, 103], [176, 92], [182, 101]]}, "A10": {"id": "A10", "polygon": [[11, 102], [79, 103], [79, 110], [95, 98], [78, 88], [78, 95], [8, 92], [8, 102]]}}, "text": {"T6": {"replacementText": "G", "value": "Full moon", "id": "T6", "rectangle": [[484, 157], [550, 179]]}, "T12": {"replacementText": "F", "value": "c", "id": "T12", "rectangle": [[259, 276], [280, 291]]}, "T11": {"replacementText": "L", "value": "B", "id": "T11", "rectangle": [[156, 261], [180, 282]]}, "T14": {"replacementText": "D", "value": "First quarter", "id": "T14", "rectangle": [[240, 297], [327, 313]]}, "T9": {"replacementText": "C", "value": "Sun's rays", "id": "T9", "rectangle": [[18, 147], [89, 165]]}, "T7": {"replacementText": "E", "value": "Earth viewed from above", "id": "T7", "rectangle": [[307, 176], [396, 213]]}, "T5": {"replacementText": "I", "value": "E", "id": "T5", "rectangle": [[463, 194], [479, 212]]}, "T13": {"replacementText": "A", "value": "D", "id": "T13", "rectangle": [[381, 260], [403, 279]]}, "T8": {"replacementText": "B", "value": "New moon", "id": "T8", "rectangle": [[158, 157], [227, 179]]}, "T10": {"replacementText": "H", "value": "A", "id": "T10", "rectangle": [[111, 189], [133, 206]]}, "T1": {"replacementText": "O", "value": "Direction of Moon's orbital motion", "id": "T1", "rectangle": [[457, 16], [556, 64]]}, "T4": {"replacementText": "N", "value": "F", "id": "T4", "rectangle": [[420, 80], [434, 101]]}, "T0": {"replacementText": "J", "value": "Last quarter", "id": "T0", "rectangle": [[254, 20], [337, 43]]}, "T2": {"replacementText": "M", "value": "H", "id": "T2", "rectangle": [[216, 55], [234, 73]]}, "T3": {"replacementText": "K", "value": "G", "id": "T3", "rectangle": [[321, 50], [343, 67]]}}, "meaningfulSpaces": {}}